{
  "$schema": "https://raw.githubusercontent.com/microsoft/AL-Go-Actions/v7.2/settings.schema.json",
  "type": "PTE",
  "templateUrl": "https://github.com/microsoft/AL-Go-PTE@main",
  "templateSha": "e2478819f6dda468d6716036ccdd2dc89dd458b6",
  "doNotRunBcptTests": true,
  "doNotRunTests": true,
  "enableCodeCop": true,
  "enableUICop": true,
  "alDoc": {
    "continuousDeployment": false
  },
  "DeliverToStorage": {
    "CreateContainerIfNotExist": true
  },
  "rulesetFile": "sp.ruleset.json",
  "enableExternalRulesets": true
}
